{
    "domain": "olicdn.com",
    "owner": {},
    "source": [
        "DuckDuckGo-US"
    ],
    "prevalence": 0.0000136,
    "sites": 2,
    "subdomains": [
        "us"
    ],
    "cnames": [],
    "fingerprinting": 2,
    "resources": [
        {
            "rule": "olicdn\\.com\\/image\\/new-user-vls95k\\.jpg@200w_200h_85q\\.webp",
            "cookies": 0,
            "fingerprinting": 0,
            "subdomains": [
                "us"
            ],
            "apis": {},
            "sites": 2,
            "prevalence": 0.0000136,
            "cnames": [],
            "responseHashes": [
                "5dc69ea121d9fa36762c137b635ea8111d10fb4bd5f6fa1181f33c3639d40cbf"
            ],
            "type": "Image",
            "firstPartyCookies": {},
            "firstPartyCookiesSent": {},
            "exampleSites": [
                "olightstore.com",
                "www.olightstore.com"
            ]
        },
        {
            "rule": "olicdn\\.com\\/_next\\/static\\/css\\/335ab14a87063931-1698804732968\\.css",
            "cookies": 0,
            "fingerprinting": 0,
            "subdomains": [
                "us"
            ],
            "apis": {},
            "sites": 2,
            "prevalence": 0.0000136,
            "cnames": [],
            "responseHashes": [
                "24c184495c8a71b4d794055fb07a5349d6fc2d869d2d9a316806c21a7a00703a"
            ],
            "type": "Stylesheet",
            "firstPartyCookies": {},
            "firstPartyCookiesSent": {},
            "exampleSites": [
                "olightstore.com",
                "www.olightstore.com"
            ]
        },
        {
            "rule": "olicdn\\.com\\/_next\\/static\\/chunks\\/1493-0d77f8b3e6f2acb4-1698804732968\\.js",
            "cookies": 0,
            "fingerprinting": 0,
            "subdomains": [
                "us"
            ],
            "apis": {},
            "sites": 2,
            "prevalence": 0.0000136,
            "cnames": [],
            "responseHashes": [
                "384178811bb82791df9d31b286b8dd46f3a59a939fb5f59a8996ae8fce8075f7"
            ],
            "type": "Script",
            "firstPartyCookies": {},
            "firstPartyCookiesSent": {},
            "exampleSites": [
                "olightstore.com",
                "www.olightstore.com"
            ]
        },
        {
            "rule": "olicdn\\.com\\/_next\\/static\\/chunks\\/2012-1b16ddc9224a782a-1698804732968\\.js",
            "cookies": 0,
            "fingerprinting": 0,
            "subdomains": [
                "us"
            ],
            "apis": {},
            "sites": 2,
            "prevalence": 0.0000136,
            "cnames": [],
            "responseHashes": [
                "15657dd5b0639f668ea02b7db664edf1028e9b505a377c96452332a9264cbc2d"
            ],
            "type": "Script",
            "firstPartyCookies": {},
            "firstPartyCookiesSent": {},
            "exampleSites": [
                "olightstore.com",
                "www.olightstore.com"
            ]
        },
        {
            "rule": "olicdn\\.com\\/_next\\/static\\/chunks\\/6281-22e292adbe64282d-1698804732968\\.js",
            "cookies": 0,
            "fingerprinting": 0,
            "subdomains": [
                "us"
            ],
            "apis": {},
            "sites": 2,
            "prevalence": 0.0000136,
            "cnames": [],
            "responseHashes": [
                "6bbf628c75efaa504667d117b28222c91777e1c21ef08683a4d8df5412f5a999"
            ],
            "type": "Script",
            "firstPartyCookies": {},
            "firstPartyCookiesSent": {},
            "exampleSites": [
                "olightstore.com",
                "www.olightstore.com"
            ]
        },
        {
            "rule": "olicdn\\.com\\/_next\\/static\\/chunks\\/3979-2aea14a1b706a89d-1698804732968\\.js",
            "cookies": 0,
            "fingerprinting": 0,
            "subdomains": [
                "us"
            ],
            "apis": {},
            "sites": 2,
            "prevalence": 0.0000136,
            "cnames": [],
            "responseHashes": [
                "557428423a36bfbc7b0eece88125196e72054bf5ef5cdd69f007f47853d44ff8"
            ],
            "type": "Script",
            "firstPartyCookies": {},
            "firstPartyCookiesSent": {},
            "exampleSites": [
                "olightstore.com",
                "www.olightstore.com"
            ]
        },
        {
            "rule": "olicdn\\.com\\/_next\\/static\\/chunks\\/815-bb0ba8412ea5a0c0-1698804732968\\.js",
            "cookies": 0,
            "fingerprinting": 0,
            "subdomains": [
                "us"
            ],
            "apis": {},
            "sites": 2,
            "prevalence": 0.0000136,
            "cnames": [],
            "responseHashes": [
                "c013204643bd1855e4413004a8601259339cc04f280c4b070b0b12f1d678c617"
            ],
            "type": "Script",
            "firstPartyCookies": {},
            "firstPartyCookiesSent": {},
            "exampleSites": [
                "olightstore.com",
                "www.olightstore.com"
            ]
        },
        {
            "rule": "olicdn\\.com\\/_next\\/static\\/chunks\\/4620-731fc0fa65393e9f-1698804732968\\.js",
            "cookies": 0,
            "fingerprinting": 0,
            "subdomains": [
                "us"
            ],
            "apis": {},
            "sites": 2,
            "prevalence": 0.0000136,
            "cnames": [],
            "responseHashes": [
                "e626754e707e2ee3fa4cdabae4f41208fff304c50ad8d1daeffbeb851cc51afc"
            ],
            "type": "Script",
            "firstPartyCookies": {},
            "firstPartyCookiesSent": {},
            "exampleSites": [
                "olightstore.com",
                "www.olightstore.com"
            ]
        },
        {
            "rule": "olicdn\\.com\\/_next\\/static\\/chunks\\/1446-65aac906e03d2e74-1698804732968\\.js",
            "cookies": 0,
            "fingerprinting": 0,
            "subdomains": [
                "us"
            ],
            "apis": {},
            "sites": 2,
            "prevalence": 0.0000136,
            "cnames": [],
            "responseHashes": [
                "4057deb05f8947f835b226d7e88dfb5b314675636b6e2b39dd3a91553576fa0c"
            ],
            "type": "Script",
            "firstPartyCookies": {},
            "firstPartyCookiesSent": {},
            "exampleSites": [
                "olightstore.com",
                "www.olightstore.com"
            ]
        },
        {
            "rule": "olicdn\\.com\\/_next\\/static\\/chunks\\/4140-910dcdd2e3834efb-1698804732968\\.js",
            "cookies": 0,
            "fingerprinting": 1,
            "subdomains": [
                "us"
            ],
            "apis": {
                "window.localStorage": 2
            },
            "sites": 2,
            "prevalence": 0.0000136,
            "cnames": [],
            "responseHashes": [
                "e7a662a1e97dcaa66ff687ec141abc4686cde2842529c1d5fb39dabafd3f130a"
            ],
            "type": "Script",
            "firstPartyCookies": {},
            "firstPartyCookiesSent": {},
            "exampleSites": [
                "olightstore.com",
                "www.olightstore.com"
            ]
        },
        {
            "rule": "olicdn\\.com\\/_next\\/static\\/chunks\\/webpack-4ea4faf6fac5666e-1698804732968\\.js",
            "cookies": 0,
            "fingerprinting": 0,
            "subdomains": [
                "us"
            ],
            "apis": {},
            "sites": 2,
            "prevalence": 0.0000136,
            "cnames": [],
            "responseHashes": [
                "e03452e8d78f3119efcdf73d830f125abb8613b5eb326e365a47e55a546cbdc5"
            ],
            "type": "Script",
            "firstPartyCookies": {},
            "firstPartyCookiesSent": {},
            "exampleSites": [
                "olightstore.com",
                "www.olightstore.com"
            ]
        },
        {
            "rule": "olicdn\\.com\\/_next\\/static\\/chunks\\/framework-932a431718b149c1-1698804732968\\.js",
            "cookies": 0,
            "fingerprinting": 1,
            "subdomains": [
                "us"
            ],
            "apis": {
                "Event.prototype.timeStamp": 2
            },
            "sites": 2,
            "prevalence": 0.0000136,
            "cnames": [],
            "responseHashes": [
                "b7fdc2c8882ab8c75f88ba9de1413522c5bca05a26808a2ebf3d83eede9ba1c8"
            ],
            "type": "Script",
            "firstPartyCookies": {},
            "firstPartyCookiesSent": {},
            "exampleSites": [
                "olightstore.com",
                "www.olightstore.com"
            ]
        },
        {
            "rule": "olicdn\\.com\\/_next\\/static\\/chunks\\/main-474feee4c21e7464-1698804732968\\.js",
            "cookies": 0,
            "fingerprinting": 1,
            "subdomains": [
                "us"
            ],
            "apis": {
                "Date.prototype.getTime": 2
            },
            "sites": 2,
            "prevalence": 0.0000136,
            "cnames": [],
            "responseHashes": [
                "d1bff81d23064a802c28664892f569675af1d2ad02b50a8a7bcc436f52eaf586"
            ],
            "type": "Script",
            "firstPartyCookies": {},
            "firstPartyCookiesSent": {},
            "exampleSites": [
                "olightstore.com",
                "www.olightstore.com"
            ]
        },
        {
            "rule": "olicdn\\.com\\/_next\\/static\\/chunks\\/runtime-9bf41eb241225d8d-1698804732968\\.js",
            "cookies": 0.0000136,
            "fingerprinting": 2,
            "subdomains": [
                "us"
            ],
            "apis": {
                "Date.prototype.getTime": 2,
                "Date.prototype.getTimezoneOffset": 2,
                "Navigator.prototype.userAgent": 2,
                "window.localStorage": 2,
                "window.name": 2,
                "window.sessionStorage": 2,
                "Document.cookie setter": 2,
                "Document.cookie getter": 2,
                "Screen.prototype.height": 2,
                "Screen.prototype.width": 2,
                "Navigator.prototype.cookieEnabled": 2,
                "window.innerHeight": 2,
                "window.innerWidth": 2,
                "Navigator.prototype.language": 2,
                "Navigator.prototype.product": 1
            },
            "sites": 2,
            "prevalence": 0.0000136,
            "cnames": [],
            "responseHashes": [
                "486d77fe632500fff567b0fd3fb561bba0ec07566771c3f4fd6dea3d082c9074"
            ],
            "type": "Script",
            "firstPartyCookies": {
                "sensorsdata_domain_test": {
                    "ttl": 2,
                    "length": 4,
                    "prevalence": 0.000013624071008658098,
                    "uniqueness": 0.5
                },
                "sajssdk_2015_cookie_access_test": {
                    "ttl": -86387,
                    "length": 1,
                    "prevalence": 0.000013624071008658098,
                    "uniqueness": 0.5
                },
                "sensorsdata2015jssdkcross": {
                    "ttl": 63072003,
                    "length": 684,
                    "prevalence": 0.000013624071008658098,
                    "uniqueness": 1
                },
                "sajssdk_2015_cross_new_user": {
                    "ttl": 63756,
                    "length": 1,
                    "prevalence": 0.000013624071008658098,
                    "uniqueness": 0.5
                }
            },
            "firstPartyCookiesSent": {},
            "exampleSites": [
                "olightstore.com",
                "www.olightstore.com"
            ]
        },
        {
            "rule": "olicdn\\.com\\/_next\\/static\\/chunks\\/mui-d3723d38-6ca8aedf015dcc68-1698804732968\\.js",
            "cookies": 0,
            "fingerprinting": 1,
            "subdomains": [
                "us"
            ],
            "apis": {
                "Navigator.prototype.userAgent": 1
            },
            "sites": 2,
            "prevalence": 0.0000136,
            "cnames": [],
            "responseHashes": [
                "ec4edfeeb0f52876b251a3d019c18ac9ac3cb0cee067b4a94fcb73218964f778"
            ],
            "type": "Script",
            "firstPartyCookies": {},
            "firstPartyCookiesSent": {},
            "exampleSites": [
                "olightstore.com",
                "www.olightstore.com"
            ]
        },
        {
            "rule": "olicdn\\.com\\/_next\\/static\\/chunks\\/mui-ac6de708-a201eb728fb2c2c7-1698804732968\\.js",
            "cookies": 0,
            "fingerprinting": 0,
            "subdomains": [
                "us"
            ],
            "apis": {},
            "sites": 2,
            "prevalence": 0.0000136,
            "cnames": [],
            "responseHashes": [
                "59f8cbcd87905b3cec5f9ca1c8143cdca988fa1c90ac837fed0c0bfba6dd1a4b"
            ],
            "type": "Script",
            "firstPartyCookies": {},
            "firstPartyCookiesSent": {},
            "exampleSites": [
                "olightstore.com",
                "www.olightstore.com"
            ]
        },
        {
            "rule": "olicdn\\.com\\/_next\\/static\\/chunks\\/mui-9700ddb9-05dc04f933c4ebf7-1698804732968\\.js",
            "cookies": 0,
            "fingerprinting": 0,
            "subdomains": [
                "us"
            ],
            "apis": {},
            "sites": 2,
            "prevalence": 0.0000136,
            "cnames": [],
            "responseHashes": [
                "da74310006d7f0e3f41dad2b61690945ed499253658e6c9e8acd7b6157e79bc9"
            ],
            "type": "Script",
            "firstPartyCookies": {},
            "firstPartyCookiesSent": {},
            "exampleSites": [
                "olightstore.com",
                "www.olightstore.com"
            ]
        },
        {
            "rule": "olicdn\\.com\\/_next\\/static\\/chunks\\/pages\\/_app-4ce619d90f8f3d35-1698804732968\\.js",
            "cookies": 0.00000681,
            "fingerprinting": 1,
            "subdomains": [
                "us"
            ],
            "apis": {
                "Document.cookie getter": 2,
                "window.localStorage": 2,
                "PerformanceTiming.prototype.navigationStart": 1,
                "Navigator.prototype.userAgent": 1,
                "Document.cookie setter": 1,
                "Date.prototype.getTime": 1
            },
            "sites": 2,
            "prevalence": 0.0000136,
            "cnames": [],
            "responseHashes": [
                "92989939c1d63c4211d5278fef8b8a03bf6ce19a83b1bad35fcdbaaebccf3d81"
            ],
            "type": "Script",
            "firstPartyCookies": {
                "deviceType": {
                    "ttl": 86400,
                    "length": 2,
                    "prevalence": 0.000006812035504329049,
                    "uniqueness": 1
                },
                "gtmFlag": {
                    "ttl": 86400,
                    "length": 4,
                    "prevalence": 0.000006812035504329049,
                    "uniqueness": 1
                },
                "TOURIST_ID": {
                    "ttl": 86400,
                    "length": 14,
                    "prevalence": 0.000006812035504329049,
                    "uniqueness": 1
                }
            },
            "firstPartyCookiesSent": {},
            "exampleSites": [
                "olightstore.com",
                "www.olightstore.com"
            ]
        },
        {
            "rule": "olicdn\\.com\\/_next\\/static\\/chunks\\/7179-91b187b318213b64-1698804732968\\.js",
            "cookies": 0,
            "fingerprinting": 0,
            "subdomains": [
                "us"
            ],
            "apis": {},
            "sites": 2,
            "prevalence": 0.0000136,
            "cnames": [],
            "responseHashes": [
                "83ff0b056a40de1f5b20ac36f561bfd896501d87ca7e503b59bae503f6bbea53"
            ],
            "type": "Script",
            "firstPartyCookies": {},
            "firstPartyCookiesSent": {},
            "exampleSites": [
                "olightstore.com",
                "www.olightstore.com"
            ]
        },
        {
            "rule": "olicdn\\.com\\/_next\\/static\\/chunks\\/787-20ee54d30f717325-1698804732968\\.js",
            "cookies": 0,
            "fingerprinting": 0,
            "subdomains": [
                "us"
            ],
            "apis": {},
            "sites": 2,
            "prevalence": 0.0000136,
            "cnames": [],
            "responseHashes": [
                "352c7206cb9d8a8f1f476be5713c1ca99363dd9263c2a465ba56f9066d1ed97f"
            ],
            "type": "Script",
            "firstPartyCookies": {},
            "firstPartyCookiesSent": {},
            "exampleSites": [
                "olightstore.com",
                "www.olightstore.com"
            ]
        },
        {
            "rule": "olicdn\\.com\\/_next\\/static\\/chunks\\/8242-54816c7cb4f4146e-1698804732968\\.js",
            "cookies": 0,
            "fingerprinting": 1,
            "subdomains": [
                "us"
            ],
            "apis": {
                "Navigator.prototype.platform": 1,
                "Navigator.prototype.userAgent": 1,
                "Screen.prototype.width": 1,
                "Screen.prototype.height": 1
            },
            "sites": 2,
            "prevalence": 0.0000136,
            "cnames": [],
            "responseHashes": [
                "61c5e08694e451ef128967a775cf4ec9d7a6f9095d2cfefe073910b5a827f162"
            ],
            "type": "Script",
            "firstPartyCookies": {},
            "firstPartyCookiesSent": {},
            "exampleSites": [
                "olightstore.com",
                "www.olightstore.com"
            ]
        },
        {
            "rule": "olicdn\\.com\\/_next\\/static\\/chunks\\/3897-40f27b91c0b40722-1698804732968\\.js",
            "cookies": 0,
            "fingerprinting": 1,
            "subdomains": [
                "us"
            ],
            "apis": {
                "Date.prototype.getTime": 2
            },
            "sites": 2,
            "prevalence": 0.0000136,
            "cnames": [],
            "responseHashes": [
                "77282d42c073615c6428a2738c18e9e1e7b2970fa589bb1b3e7fd744ffa7790c"
            ],
            "type": "Script",
            "firstPartyCookies": {},
            "firstPartyCookiesSent": {},
            "exampleSites": [
                "olightstore.com",
                "www.olightstore.com"
            ]
        },
        {
            "rule": "olicdn\\.com\\/_next\\/static\\/chunks\\/9912-3b343670df19d21b-1698804732968\\.js",
            "cookies": 0,
            "fingerprinting": 0,
            "subdomains": [
                "us"
            ],
            "apis": {},
            "sites": 2,
            "prevalence": 0.0000136,
            "cnames": [],
            "responseHashes": [
                "4ca96154b0b4beb9d0479e41f0f1f834466df094a3b5b1f48df534dcedb7dcb1"
            ],
            "type": "Script",
            "firstPartyCookies": {},
            "firstPartyCookiesSent": {},
            "exampleSites": [
                "olightstore.com",
                "www.olightstore.com"
            ]
        },
        {
            "rule": "olicdn\\.com\\/_next\\/static\\/chunks\\/536-2008d9f18da1d57d-1698804732968\\.js",
            "cookies": 0,
            "fingerprinting": 0,
            "subdomains": [
                "us"
            ],
            "apis": {},
            "sites": 2,
            "prevalence": 0.0000136,
            "cnames": [],
            "responseHashes": [
                "8738335bb6247f4da514676e6bb4f5d539ed440c0810ba817d239ab78d7ac7a5"
            ],
            "type": "Script",
            "firstPartyCookies": {},
            "firstPartyCookiesSent": {},
            "exampleSites": [
                "olightstore.com",
                "www.olightstore.com"
            ]
        },
        {
            "rule": "olicdn\\.com\\/_next\\/static\\/chunks\\/9535-06c2eac68ef06ad2-1698804732968\\.js",
            "cookies": 0,
            "fingerprinting": 1,
            "subdomains": [
                "us"
            ],
            "apis": {
                "Date.prototype.getTime": 1
            },
            "sites": 2,
            "prevalence": 0.0000136,
            "cnames": [],
            "responseHashes": [
                "c381de99eddd741304610f836bd223067c2f4a33178bb0ff913cc47ea33c4fdc"
            ],
            "type": "Script",
            "firstPartyCookies": {},
            "firstPartyCookiesSent": {},
            "exampleSites": [
                "olightstore.com",
                "www.olightstore.com"
            ]
        },
        {
            "rule": "olicdn\\.com\\/_next\\/static\\/a2128e0444671e8a_1698804732968\\/_buildManifest\\.js",
            "cookies": 0,
            "fingerprinting": 0,
            "subdomains": [
                "us"
            ],
            "apis": {},
            "sites": 2,
            "prevalence": 0.0000136,
            "cnames": [],
            "responseHashes": [
                "b2ac016f54d8d6e80223d22c76be1381de6eee47484baab7c684e1aad3683fd1"
            ],
            "type": "Script",
            "firstPartyCookies": {},
            "firstPartyCookiesSent": {},
            "exampleSites": [
                "olightstore.com",
                "www.olightstore.com"
            ]
        },
        {
            "rule": "olicdn\\.com\\/_next\\/static\\/a2128e0444671e8a_1698804732968\\/_ssgManifest\\.js",
            "cookies": 0,
            "fingerprinting": 0,
            "subdomains": [
                "us"
            ],
            "apis": {},
            "sites": 2,
            "prevalence": 0.0000136,
            "cnames": [],
            "responseHashes": [
                "eb1bcb3070809eceaf4be98e36f4ef5420a96d725835f5341c8b6198ef3bf4fb"
            ],
            "type": "Script",
            "firstPartyCookies": {},
            "firstPartyCookiesSent": {},
            "exampleSites": [
                "olightstore.com",
                "www.olightstore.com"
            ]
        },
        {
            "rule": "olicdn\\.com\\/image\\/logo-dwfy1o\\.png",
            "cookies": 0,
            "fingerprinting": 0,
            "subdomains": [
                "us"
            ],
            "apis": {},
            "sites": 2,
            "prevalence": 0.0000136,
            "cnames": [],
            "responseHashes": [
                "d0939a912a44c405a9aaa58d0e43864ba143696853cfb07cea192a0748ef9f63"
            ],
            "type": "Image",
            "firstPartyCookies": {},
            "firstPartyCookiesSent": {},
            "exampleSites": [
                "olightstore.com",
                "www.olightstore.com"
            ]
        },
        {
            "rule": "olicdn\\.com\\/assets\\/font\\/iconfont\\/iconfont\\.woff2",
            "cookies": 0,
            "fingerprinting": 0,
            "subdomains": [
                "us"
            ],
            "apis": {},
            "sites": 2,
            "prevalence": 0.0000136,
            "cnames": [],
            "responseHashes": [
                "621f3c0738dce9b9c84203c785a3507775bda6971a40ce29af17850abb10f53c"
            ],
            "type": "Font",
            "firstPartyCookies": {},
            "firstPartyCookiesSent": {},
            "exampleSites": [
                "olightstore.com",
                "www.olightstore.com"
            ]
        },
        {
            "rule": "olicdn\\.com\\/assets\\/font\\/Inter\\/Inter-UI-Regular\\.woff2",
            "cookies": 0,
            "fingerprinting": 0,
            "subdomains": [
                "us"
            ],
            "apis": {},
            "sites": 2,
            "prevalence": 0.0000136,
            "cnames": [],
            "responseHashes": [
                "64eb8ce7d3f67136a7b81f37396a6b3b5243b308cba8ee4806d9d0a6d8c29b7a"
            ],
            "type": "Font",
            "firstPartyCookies": {},
            "firstPartyCookiesSent": {},
            "exampleSites": [
                "olightstore.com",
                "www.olightstore.com"
            ]
        },
        {
            "rule": "olicdn\\.com\\/assets\\/js\\/webPopup\\.min\\.js",
            "cookies": 0,
            "fingerprinting": 1,
            "subdomains": [
                "us"
            ],
            "apis": {
                "window.localStorage": 2,
                "Screen.prototype.width": 2
            },
            "sites": 2,
            "prevalence": 0.0000136,
            "cnames": [],
            "responseHashes": [
                "43d085e9d8c9e1a9740a63adf10f2ba2273d295b5a743569430deb998c448b3d"
            ],
            "type": "Script",
            "firstPartyCookies": {},
            "firstPartyCookiesSent": {},
            "exampleSites": [
                "olightstore.com",
                "www.olightstore.com"
            ]
        },
        {
            "rule": "olicdn\\.com\\/assets\\/js\\/abtest\\.min\\.js",
            "cookies": 0,
            "fingerprinting": 1,
            "subdomains": [
                "us"
            ],
            "apis": {
                "window.localStorage": 2,
                "Date.prototype.getTime": 2,
                "Navigator.prototype.userAgent": 2
            },
            "sites": 2,
            "prevalence": 0.0000136,
            "cnames": [],
            "responseHashes": [
                "fd80e71ecb275927c98ea78d25dccbe1d5395fa2be22fda1bbf9e895be6a2e0c"
            ],
            "type": "Script",
            "firstPartyCookies": {},
            "firstPartyCookiesSent": {},
            "exampleSites": [
                "olightstore.com",
                "www.olightstore.com"
            ]
        },
        {
            "rule": "olicdn\\.com\\/_next\\/static\\/chunks\\/2036-9828ad94d6f1ee66-1698804732968\\.js",
            "cookies": 0,
            "fingerprinting": 0,
            "subdomains": [
                "us"
            ],
            "apis": {},
            "sites": 2,
            "prevalence": 0.0000136,
            "cnames": [],
            "responseHashes": [
                "48b81280fa820980683fa02ba6b0004c1a26b6263a6244f69d4356c2905f877c"
            ],
            "type": "Script",
            "firstPartyCookies": {},
            "firstPartyCookiesSent": {},
            "exampleSites": [
                "olightstore.com",
                "www.olightstore.com"
            ]
        },
        {
            "rule": "olicdn\\.com\\/_next\\/static\\/chunks\\/7737-dd0cf2858d2fe268-1698804732968\\.js",
            "cookies": 0,
            "fingerprinting": 0,
            "subdomains": [
                "us"
            ],
            "apis": {},
            "sites": 2,
            "prevalence": 0.0000136,
            "cnames": [],
            "responseHashes": [
                "e4d5ba993e4c869d46d51622ae4389e6418d0cc9fda9c55e9a6cd9beb65039cb"
            ],
            "type": "Script",
            "firstPartyCookies": {},
            "firstPartyCookiesSent": {},
            "exampleSites": [
                "olightstore.com",
                "www.olightstore.com"
            ]
        }
    ],
    "categories": [],
    "performance": {},
    "cookies": 0.0000136,
    "topInitiators": [
        {
            "domain": "first party",
            "prevalence": 1
        }
    ],
    "types": {
        "Image": 4,
        "Stylesheet": 2,
        "Script": 58,
        "Font": 4
    },
    "nameservers": [
        "ns-666.awsdns-19.net",
        "ns-204.awsdns-25.com",
        "ns-1629.awsdns-11.co.uk",
        "ns-1314.awsdns-36.org"
    ]
}