{
    "domain": "tnhs.cloud",
    "owner": {},
    "source": [
        "DuckDuckGo-US"
    ],
    "prevalence": 0.0000613,
    "sites": 9,
    "subdomains": [
        "mfah-tnew-prod",
        "nash-tnew-prod",
        "natt-tnew-prod",
        "nmsc-tnew-test"
    ],
    "cnames": [
        {
            "original": "my.mfah.org",
            "resolved": "mfah-tnew-prod.tnhs.cloud"
        },
        {
            "original": "tickets.nashvillesymphony.org",
            "resolved": "nash-tnew-prod.tnhs.cloud"
        },
        {
            "original": "tickets.nationaltheatre.org.uk",
            "resolved": "natt-tnew-prod.tnhs.cloud"
        }
    ],
    "fingerprinting": 0,
    "resources": [
        {
            "rule": "tnhs\\.cloud\\/api\\/session\\/sessionkey",
            "cookies": 0.0000272,
            "fingerprinting": 0,
            "subdomains": [
                "mfah-tnew-prod",
                "nash-tnew-prod",
                "natt-tnew-prod"
            ],
            "apis": {},
            "sites": 4,
            "prevalence": 0.0000272,
            "cnames": [
                {
                    "original": "my.mfah.org",
                    "resolved": "mfah-tnew-prod.tnhs.cloud"
                },
                {
                    "original": "tickets.nashvillesymphony.org",
                    "resolved": "nash-tnew-prod.tnhs.cloud"
                },
                {
                    "original": "tickets.nationaltheatre.org.uk",
                    "resolved": "natt-tnew-prod.tnhs.cloud"
                }
            ],
            "responseHashes": [
                "0480bf06794279bb393efd45a1eef4ef4a233f0a432555f64e3c64561825cd90",
                "01e08fab9d834e11d9112e6a9b0196f44fe156179b4f98ad81e2b0720a936542",
                "a0abbb05c7251fb29b412789ff92848d397d54ddd9b24507c9f1430a5c2278b0"
            ],
            "type": "Fetch",
            "firstPartyCookies": {},
            "firstPartyCookiesSent": {},
            "exampleSites": [
                "mfah.org",
                "www.mfah.org",
                "www.nashvillesymphony.org",
                "www.nationaltheatre.org.uk"
            ]
        },
        {
            "rule": "tnhs\\.cloud\\/components\\/sharedsession",
            "cookies": 0.00000681,
            "fingerprinting": 0,
            "subdomains": [
                "nmsc-tnew-test"
            ],
            "apis": {},
            "sites": 2,
            "prevalence": 0.0000136,
            "cnames": [],
            "responseHashes": [],
            "type": "XHR",
            "firstPartyCookies": {},
            "firstPartyCookiesSent": {},
            "exampleSites": [
                "nms.ac.uk",
                "www.nms.ac.uk"
            ]
        }
    ],
    "categories": [],
    "performance": {},
    "cookies": 0.0000613,
    "topInitiators": [
        {
            "domain": "cloudflare.com",
            "prevalence": 0.5
        },
        {
            "domain": "ajax.googleapis.com",
            "prevalence": 0.25
        },
        {
            "domain": "jquery.com",
            "prevalence": 0.25
        }
    ],
    "types": {
        "Fetch": 4,
        "XHR": 2
    },
    "nameservers": [
        "ns-1438.awsdns-51.org",
        "ns-477.awsdns-59.com",
        "ns-1737.awsdns-25.co.uk",
        "ns-885.awsdns-46.net"
    ]
}